hvpdb_http/__init__.py
hvpdb_http-0.1.0.dist-info/METADATA
hvpdb_http-0.1.0.dist-info/WHEEL
hvpdb_http-0.1.0.dist-info/entry_points.txt
hvpdb_http-0.1.0.dist-info/top_level.txt
hvpdb_http-0.1.0.dist-info/RECORD
