Metadata-Version: 2.4
Name: hvpdb-http
Version: 0.1.0
Summary: HTTP API Server Plugin for HVPDB
Requires-Dist: fastapi
Requires-Dist: uvicorn
Requires-Dist: hvpdb
Dynamic: requires-dist
Dynamic: summary
